{
    "taskDefinitionArn": "arn:aws:ecs:ap-south-1:209483893123:task-definition/default-galani-enterprise:19",
    "containerDefinitions": [
        {
            "name": "Main",
            "image": "209483893123.dkr.ecr.ap-south-1.amazonaws.com/galani-enterprise@sha256:3b4011bafe296e4ab61b0e1db5143b79eb75e3e4e17aa42b92462a76697d5347",
            "cpu": 0,
            "portMappings": [
                {
                    "containerPort": 8000,
                    "hostPort": 8000,
                    "protocol": "tcp"
                }
            ],
            "essential": true,
            "command": [
                "uvicorn",
                "main:app",
                "--host",
                "0.0.0.0",
                "--port",
                "8000"
            ],
            "environment": [],
            "mountPoints": [],
            "volumesFrom": [],
            "logConfiguration": {
                "logDriver": "awslogs",
                "options": {
                    "awslogs-group": "/aws/ecs/galani-api",
                    "awslogs-region": "ap-south-1",
                    "awslogs-stream-prefix": "ecs"
                }
            },
            "systemControls": []
        }
    ],
    "family": "default-galani-enterprise",
    "taskRoleArn": "arn:aws:iam::209483893123:role/galani-task-role",
    "executionRoleArn": "arn:aws:iam::209483893123:role/ecsTaskExecutionRole",
    "networkMode": "awsvpc",
    "revision": 19,
    "volumes": [],
    "status": "ACTIVE",
    "requiresAttributes": [
        {
            "name": "com.amazonaws.ecs.capability.logging-driver.awslogs"
        },
        {
            "name": "ecs.capability.execution-role-awslogs"
        },
        {
            "name": "com.amazonaws.ecs.capability.ecr-auth"
        },
        {
            "name": "com.amazonaws.ecs.capability.docker-remote-api.1.19"
        },
        {
            "name": "com.amazonaws.ecs.capability.docker-remote-api.1.21"
        },
        {
            "name": "com.amazonaws.ecs.capability.task-iam-role"
        },
        {
            "name": "ecs.capability.execution-role-ecr-pull"
        },
        {
            "name": "com.amazonaws.ecs.capability.docker-remote-api.1.18"
        },
        {
            "name": "ecs.capability.task-eni"
        }
    ],
    "placementConstraints": [],
    "compatibilities": [
        "EC2",
        "MANAGED_INSTANCES",
        "FARGATE"
    ],
    "requiresCompatibilities": [
        "FARGATE"
    ],
    "cpu": "512",
    "memory": "1024",
    "registeredAt": "2026-01-04T22:37:15.997000+05:30",
    "registeredBy": "arn:aws:iam::209483893123:user/galani-admin"
}
